ranch/__init__.py
ranch/__version__.py
ranch/_logger.py
ranch/_retry.py
ranch/_utils.py
ranch/connection.py
ranch/exceptions.py
ranch/job.py
ranch/ranchecker.py
ranch/uploadJob.py
ranch_sdk-1.0.18.dist-info/METADATA
ranch_sdk-1.0.18.dist-info/WHEEL
ranch_sdk-1.0.18.dist-info/top_level.txt
ranch_sdk-1.0.18.dist-info/RECORD
