Metadata-Version: 2.1
Name: ranch-sdk
Version: 1.0.18
Summary: ranchcomputing SDK stands as a bridge between external pipelines and our rendering services
Home-page: https://www.ranchcomputing.com
Author: mohamed bakhouche
Author-email: dev@ranchcomputing.com
License: MIT
Project-URL: Documentation, https://download.ranchcomputing.com/dl/ranch_online/ranchsdk/guide/usage.html
Project-URL: Source, https://github.com/ranchcomputing/python-sdk
Platform: UNKNOWN
Classifier: Development Status :: 3 - Alpha
Classifier: Intended Audience :: Developers
Classifier: Topic :: Utilities
Classifier: Programming Language :: Python :: 3.10
Classifier: Programming Language :: Python :: 3.11
Classifier: Programming Language :: Python :: 3.12
Classifier: Programming Language :: Python :: 3.13
Classifier: License :: OSI Approved :: Apache Software License
Requires-Python: >=3.10,<3.14
Requires-Dist: requests
Requires-Dist: bson
Requires-Dist: twine
Requires-Dist: wheel
Requires-Dist: boto3
Requires-Dist: tuspy
